rdatapp/__init__.py
rdatapp/categorical_encoder.py
rdatapp/data_type_converter.py
rdatapp/datetime_handler.py
rdatapp/feature_engineer.py
rdatapp/missing_value_handler.py
rdatapp/outlier_handler.py
rdatapp/scaler.py
rdatapp/text_cleaner.py
rdatapp-1.0.dist-info/METADATA
rdatapp-1.0.dist-info/WHEEL
rdatapp-1.0.dist-info/top_level.txt
rdatapp-1.0.dist-info/RECORD
