Metadata-Version: 2.1
Name: rdatapp
Version: 1.0
Summary: A recoded data preprocessing library for handling various data cleaning and transformation tasks. The library includes classes for text cleaning, missing value imputation, one-hot encoding, and more.
Home-page: https://github.com/Beegash/Recoded-Data-Processing-Library
Author: Izzettin Furkan Özmen, Ismail Cifci
Author-email: izzettinfurkan.ozmen@stu.fsm.edu.tr, ismail.cifci@stu.fsm.edu.tr
Project-URL: Source, https://github.com/Beegash/Recoded-Data-Processing-Library
Keywords: data preprocessing data-cleaning one-hot-encoding text-cleaning missing-value-imputation
Classifier: Development Status :: 6 - Mature
Classifier: Intended Audience :: Developers
Classifier: Intended Audience :: Education
Classifier: Programming Language :: Python :: 3
Classifier: Programming Language :: Python :: 3.6
Classifier: Programming Language :: Python :: 3.7
Classifier: Programming Language :: Python :: 3.8
Classifier: Programming Language :: Python :: 3.9
Classifier: Programming Language :: Python :: 3.10
Classifier: Programming Language :: Python :: 3.11
Classifier: Operating System :: OS Independent
Classifier: Topic :: Software Development :: Libraries :: Python Modules
Classifier: Topic :: Scientific/Engineering :: Information Analysis
Requires-Python: >=3.6
Requires-Dist: pandas
Requires-Dist: numpy
Requires-Dist: scikit-learn
Requires-Dist: nltk
